ai_infra/__init__.py
ai_infra/callbacks.py
ai_infra/cli/README.md
ai_infra/cli/__init__.py
ai_infra/cli/cmds/__init__.py
ai_infra/cli/cmds/chat_cmds.py
ai_infra/cli/cmds/discovery_cmds.py
ai_infra/cli/cmds/help.py
ai_infra/cli/cmds/imagegen_cmds.py
ai_infra/cli/cmds/mcp_cmds.py
ai_infra/cli/cmds/multimodal_cmds.py
ai_infra/cli/cmds/stdio_publisher_cmds.py
ai_infra/embeddings/__init__.py
ai_infra/embeddings/embeddings.py
ai_infra/embeddings/vectorstore.py
ai_infra/errors.py
ai_infra/graph/__init__.py
ai_infra/graph/graph.py
ai_infra/graph/models.py
ai_infra/graph/utils.py
ai_infra/imagegen/__init__.py
ai_infra/imagegen/discovery.py
ai_infra/imagegen/imagegen.py
ai_infra/imagegen/models.py
ai_infra/llm/__init__.py
ai_infra/llm/agent.py
ai_infra/llm/agents/__init__.py
ai_infra/llm/agents/callbacks.py
ai_infra/llm/agents/custom/__init__.py
ai_infra/llm/agents/deep.py
ai_infra/llm/auth.py
ai_infra/llm/base.py
ai_infra/llm/defaults.py
ai_infra/llm/llm.py
ai_infra/llm/memory/__init__.py
ai_infra/llm/memory/context.py
ai_infra/llm/memory/store.py
ai_infra/llm/memory/summarize.py
ai_infra/llm/memory/tokens.py
ai_infra/llm/memory/trim.py
ai_infra/llm/multimodal/__init__.py
ai_infra/llm/multimodal/audio.py
ai_infra/llm/multimodal/audio_output.py
ai_infra/llm/multimodal/discovery.py
ai_infra/llm/multimodal/models.py
ai_infra/llm/multimodal/stt.py
ai_infra/llm/multimodal/tts.py
ai_infra/llm/multimodal/vision.py
ai_infra/llm/personas.py
ai_infra/llm/providers/__init__.py
ai_infra/llm/providers/discovery.py
ai_infra/llm/providers/providers.py
ai_infra/llm/realtime/__init__.py
ai_infra/llm/realtime/base.py
ai_infra/llm/realtime/gemini.py
ai_infra/llm/realtime/models.py
ai_infra/llm/realtime/openai.py
ai_infra/llm/realtime/utils.py
ai_infra/llm/realtime/voice.py
ai_infra/llm/session.py
ai_infra/llm/streaming.py
ai_infra/llm/tools/__init__.py
ai_infra/llm/tools/approval.py
ai_infra/llm/tools/custom/__init__.py
ai_infra/llm/tools/custom/cli.py
ai_infra/llm/tools/custom/memory.py
ai_infra-1.1.1.dist-info/LICENSE
ai_infra-1.1.1.dist-info/METADATA
ai_infra-1.1.1.dist-info/WHEEL
ai_infra-1.1.1.dist-info/entry_points.txt
ai_infra-1.1.1.dist-info/RECORD
