Metadata-Version: 2.3
Name: ai-infra
Version: 1.1.1
Summary: Infrastructure for efficient and scalable AI applications.
License: MIT
Keywords: ai,langchain,langgraph,fastapi,infra,llm,mcp
Author: Ali Khatami
Author-email: aliikhatami94@gmail.com
Requires-Python: >=3.11,<4.0
Classifier: Development Status :: 5 - Production/Stable
Classifier: Framework :: FastAPI
Classifier: Intended Audience :: Developers
Classifier: License :: OSI Approved :: MIT License
Classifier: Programming Language :: Python :: 3
Classifier: Programming Language :: Python :: 3.11
Classifier: Programming Language :: Python :: 3.12
Classifier: Programming Language :: Python :: 3.13
Classifier: Programming Language :: Python :: 3 :: Only
Classifier: Topic :: Scientific/Engineering :: Artificial Intelligence
Classifier: Topic :: Software Development :: Libraries :: Python Modules
Classifier: Typing :: Typed
Provides-Extra: anthropic
Provides-Extra: chroma
Provides-Extra: csv
Provides-Extra: docx
Provides-Extra: faiss
Provides-Extra: google
Provides-Extra: html
Provides-Extra: huggingface
Provides-Extra: llm-all
Provides-Extra: local-embeddings
Provides-Extra: pdf
Provides-Extra: pinecone
Provides-Extra: postgres
Provides-Extra: qdrant
Provides-Extra: retriever
Provides-Extra: retriever-all
Provides-Extra: retriever-local
Provides-Extra: sqlite
Provides-Extra: xai
Requires-Dist: deepagents (>=0.2.0)
Requires-Dist: fastapi (>=0.110.0)
Requires-Dist: google-genai (>=1.0.0) ; extra == "google" or extra == "llm-all"
Requires-Dist: langchain (>=1.0.0)
Requires-Dist: langchain-anthropic (>=1.0.0) ; extra == "anthropic" or extra == "llm-all"
Requires-Dist: langchain-google-genai (>=3.0.0) ; extra == "google" or extra == "llm-all"
Requires-Dist: langchain-huggingface (>=1.0.0) ; extra == "local-embeddings" or extra == "huggingface" or extra == "retriever-local"
Requires-Dist: langchain-mcp-adapters (>=0.1.0)
Requires-Dist: langchain-openai (>=1.0.0)
Requires-Dist: langchain-text-splitters (>=0.3.0)
Requires-Dist: langchain-xai (>=1.0.0) ; extra == "xai" or extra == "llm-all"
Requires-Dist: langgraph (>=1.0.0)
Requires-Dist: langsmith (>=0.4.0)
Requires-Dist: mcp[cli] (>=1.0.0)
Requires-Dist: numpy (>=1.24.0)
Requires-Dist: pydantic (>=2.0)
Requires-Dist: python-dotenv (>=1.0.0)
Requires-Dist: pyyaml (>=6.0)
Requires-Dist: sentence-transformers (>=5.0.0) ; extra == "local-embeddings" or extra == "huggingface" or extra == "retriever-local"
Requires-Dist: svc-infra (>=0.1.0)
Project-URL: Documentation, https://nfrax.com/ai-infra
Project-URL: Homepage, https://github.com/nfraxlab/ai-infra
Project-URL: Issues, https://github.com/nfraxlab/ai-infra/issues
Project-URL: Repository, https://github.com/nfraxlab/ai-infra
